postprocessing_seismo_lib/__init__.py
postprocessing_seismo_lib/utils.py
postprocessing_seismo_lib/utils_OLDER.py
postprocessing_seismo_lib/utils_OLDERV4_OnsetNotCommented.py
postprocessing_seismo_lib/utils_OLDERV5_pickfilterNotFlexibleEnough.py
postprocessing_seismo_lib/utils_OLDERV6_dataretrievalnotupdate.py
postprocessing_seismo_lib/utils_olderV2.py
postprocessing_seismo_lib/utils_olderV3.py
postprocessing_seismo_lib/example_data/40584759_csv.json
postprocessing_seismo_lib/example_data/40584759_events_test.xml
postprocessing_seismo_lib/example_data/40584759_events_testGOUA
postprocessing_seismo_lib/example_data/40584759_gamma_events.csv
postprocessing_seismo_lib/example_data/40584759_gamma_picks.csv
postprocessing_seismo_lib/example_data/78827847.json
postprocessing_seismo_lib/example_data/xxxx_file_containing_filtered_picks.json
postprocessing_seismo_lib/example_data/xxxx_file_containing_picks.json
postprocessing_seismo_lib/example_data/z78966423_api_stproc_9999.arcout
postprocessing_seismo_lib-0.1.61.dist-info/licenses/LICENSE
postprocessing_seismo_lib-0.1.61.dist-info/METADATA
postprocessing_seismo_lib-0.1.61.dist-info/WHEEL
postprocessing_seismo_lib-0.1.61.dist-info/top_level.txt
postprocessing_seismo_lib-0.1.61.dist-info/RECORD
