Metadata-Version: 2.4
Name: postprocessing_seismo_lib
Version: 0.1.61
Summary: A library for building and parsing Seismology API message bodies.
Author: Ryan Tam
Author-email: rwtam@caltech.edu
Project-URL: Documentation, https://pypi-postprocessing-seismic-data.readthedocs.io/en/latest/
Project-URL: Log Issues, https://scsngit.gps.caltech.edu/services/postprocessing-library/-/issues
Project-URL: Seismo-Service, https://github.com/SCEDC/seismo-service
Classifier: Programming Language :: Python :: 3
Classifier: Operating System :: OS Independent
Requires-Python: >=3.10
License-File: LICENSE
Requires-Dist: jsonschema>=4.0.0
Requires-Dist: pandas
Requires-Dist: xmltodict
Requires-Dist: importlib_resources; python_version < "3.7"
Dynamic: author
Dynamic: author-email
Dynamic: classifier
Dynamic: description
Dynamic: description-content-type
Dynamic: license-file
Dynamic: project-url
Dynamic: provides-extra
Dynamic: requires-dist
Dynamic: requires-python
Dynamic: summary
